tracekit/__init__.py
tracekit/__main__.py
tracekit/exceptions.py
tracekit/py.typed
tracekit/analyzers/__init__.py
tracekit/analyzers/measurements.py
tracekit/analyzers/validation.py
tracekit/analyzers/digital/__init__.py
tracekit/analyzers/digital/bus.py
tracekit/analyzers/digital/clock.py
tracekit/analyzers/digital/correlation.py
tracekit/analyzers/digital/edges.py
tracekit/analyzers/digital/extraction.py
tracekit/analyzers/digital/quality.py
tracekit/analyzers/digital/signal_quality.py
tracekit/analyzers/digital/thresholds.py
tracekit/analyzers/digital/timing.py
tracekit/analyzers/eye/__init__.py
tracekit/analyzers/eye/diagram.py
tracekit/analyzers/eye/metrics.py
tracekit/analyzers/jitter/__init__.py
tracekit/analyzers/jitter/ber.py
tracekit/analyzers/jitter/decomposition.py
tracekit/analyzers/jitter/measurements.py
tracekit/analyzers/jitter/spectrum.py
tracekit/analyzers/packet/__init__.py
tracekit/analyzers/packet/daq.py
tracekit/analyzers/packet/metrics.py
tracekit/analyzers/packet/parser.py
tracekit/analyzers/packet/payload.py
tracekit/analyzers/packet/payload_analysis.py
tracekit/analyzers/packet/payload_extraction.py
tracekit/analyzers/packet/payload_patterns.py
tracekit/analyzers/packet/stream.py
tracekit/analyzers/patterns/__init__.py
tracekit/analyzers/patterns/clustering.py
tracekit/analyzers/patterns/discovery.py
tracekit/analyzers/patterns/learning.py
tracekit/analyzers/patterns/matching.py
tracekit/analyzers/patterns/periodic.py
tracekit/analyzers/patterns/sequences.py
tracekit/analyzers/power/__init__.py
tracekit/analyzers/power/ac_power.py
tracekit/analyzers/power/basic.py
tracekit/analyzers/power/conduction.py
tracekit/analyzers/power/efficiency.py
tracekit/analyzers/power/ripple.py
tracekit/analyzers/power/soa.py
tracekit/analyzers/power/switching.py
tracekit/analyzers/protocol/__init__.py
tracekit/analyzers/protocols/__init__.py
tracekit/analyzers/protocols/base.py
tracekit/analyzers/protocols/can.py
tracekit/analyzers/protocols/can_fd.py
tracekit-0.3.1.dist-info/METADATA
tracekit-0.3.1.dist-info/WHEEL
tracekit-0.3.1.dist-info/entry_points.txt
tracekit-0.3.1.dist-info/licenses/LICENSE
tracekit-0.3.1.dist-info/RECORD
