Metadata-Version: 2.4
Name: tracekit
Version: 0.3.1
Summary: Reverse engineer ANY system from captured waveforms—analog or digital. Audio (THD/SNR), power (ripple/efficiency), RF, sensors, IoT protocols (UART/SPI/I2C/CAN), state machines, CRC recovery. IEEE-compliant (181/1241/1459/2414)
Project-URL: Homepage, https://github.com/lair-click-bats/tracekit
Project-URL: Documentation, https://github.com/lair-click-bats/tracekit/tree/main/docs
Project-URL: Repository, https://github.com/lair-click-bats/tracekit
Project-URL: Changelog, https://github.com/lair-click-bats/tracekit/blob/main/CHANGELOG.md
Project-URL: Issue Tracker, https://github.com/lair-click-bats/tracekit/issues
Project-URL: Discussions, https://github.com/lair-click-bats/tracekit/discussions
License-Expression: MIT
License-File: LICENSE
Keywords: automotive,can,cispr,embedded-systems,emc-testing,eye-diagram,flexray,hardware-debugging,i2c,ieee-1241,ieee-181,ieee-2414,jitter-analysis,jtag,lin,logic-analyzer,oscilloscope,protocol-decoder,protocol-inference,reverse-engineering,signal-analysis,signal-integrity,spectral-analysis,spi,state-machine-learning,swd,uart,waveform-analysis
Classifier: Development Status :: 4 - Beta
Classifier: Intended Audience :: Developers
Classifier: Intended Audience :: Manufacturing
Classifier: Intended Audience :: Science/Research
Classifier: License :: OSI Approved :: MIT License
Classifier: Operating System :: OS Independent
Classifier: Programming Language :: Python :: 3
Classifier: Programming Language :: Python :: 3.12
Classifier: Programming Language :: Python :: 3.13
Classifier: Topic :: Scientific/Engineering
Classifier: Topic :: Scientific/Engineering :: Electronic Design Automation (EDA)
Classifier: Topic :: Scientific/Engineering :: Information Analysis
Classifier: Topic :: System :: Hardware
Classifier: Typing :: Typed
Requires-Python: >=3.12
Requires-Dist: bokeh>=3.8.1
Requires-Dist: click>=8.1.0
Requires-Dist: jinja2>=3.1
Requires-Dist: matplotlib>=3.7.0
Requires-Dist: numpy>=1.24.0
Requires-Dist: pandas>=2.0.0
Requires-Dist: plotly>=6.5.0
Requires-Dist: psutil>=5.9.0
Requires-Dist: pyyaml>=6.0
Requires-Dist: reportlab>=4.4.7
Requires-Dist: scipy>=1.10.0
Requires-Dist: tm-data-types>=0.3.0
Provides-Extra: all
Requires-Dist: asammdf<8.0.0,>=7.4.0; extra == 'all'
Requires-Dist: cantools>=39.4.0; extra == 'all'
Requires-Dist: check-jsonschema>=0.29.0; extra == 'all'
Requires-Dist: h5py>=3.0.0; extra == 'all'
Requires-Dist: interrogate>=1.7.0; extra == 'all'
Requires-Dist: ipython>=8.0.0; extra == 'all'
Requires-Dist: jupyter>=1.0.0; extra == 'all'
Requires-Dist: pytest-cov>=6.0; extra == 'all'
Requires-Dist: pytest-timeout>=2.3.0; extra == 'all'
Requires-Dist: pytest>=8.0; extra == 'all'
Requires-Dist: python-can>=4.4.0; extra == 'all'
Requires-Dist: python-pptx>=0.6.21; extra == 'all'
Requires-Dist: reportlab>=4.0.0; extra == 'all'
Requires-Dist: types-pyyaml>=6.0; extra == 'all'
Requires-Dist: yamllint>=1.35; extra == 'all'
Provides-Extra: automotive
Requires-Dist: asammdf<8.0.0,>=7.4.0; extra == 'automotive'
Requires-Dist: cantools>=39.4.0; extra == 'automotive'
Requires-Dist: python-can>=4.4.0; extra == 'automotive'
Provides-Extra: dev
Requires-Dist: check-jsonschema>=0.29.0; extra == 'dev'
Requires-Dist: interrogate>=1.7.0; extra == 'dev'
Requires-Dist: pytest-cov>=6.0; extra == 'dev'
Requires-Dist: pytest-timeout>=2.3.0; extra == 'dev'
Requires-Dist: pytest>=8.0; extra == 'dev'
Requires-Dist: types-pyyaml>=6.0; extra == 'dev'
Requires-Dist: yamllint>=1.35; extra == 'dev'
Provides-Extra: hdf5
Requires-Dist: h5py>=3.0.0; extra == 'hdf5'
Provides-Extra: jupyter
Requires-Dist: ipython>=8.0.0; extra == 'jupyter'
Requires-Dist: jupyter>=1.0.0; extra == 'jupyter'
Provides-Extra: reporting
Requires-Dist: python-pptx>=0.6.21; extra == 'reporting'
Requires-Dist: reportlab>=4.0.0; extra == 'reporting'
